setup.py
opendns/__init__.py
opendns/opendns.py
opendns.egg-info/PKG-INFO
opendns.egg-info/SOURCES.txt
opendns.egg-info/dependency_links.txt
opendns.egg-info/entry_points.txt
opendns.egg-info/top_level.txt