Metadata-Version: 1.1
Name: opendns
Version: 0.1.0
Summary: Small set of utilities to work with OpenDNS from Python
Home-page: UNKNOWN
Author: Sergio Fernández
Author-email: sergio.fernandez@redlink.co
License: UNKNOWN
Keywords: python opendns ip network
Platform: any
Classifier: Development Status :: 4 - Beta
Classifier: Intended Audience :: Developers
Classifier: Topic :: System :: Networking
Classifier: Programming Language :: Python :: 2
Classifier: Programming Language :: Python :: 3
Classifier: Environment :: Console
